{"pair.4.5": "hit", "pair.7.4": "split", "hard.13.6": "stick", "soft.14.3": "hit", "pair.9.8": "stick", "soft.22.6": "stick", "hard.18.4": "stick", "hard.11.8": "double", "pair.1.8": "split", "soft.13.4": "hit", "hard.17.2": "stick", "hard.18.2": "stick", "pair.6.7": "hit", "pair.2.3": "hit", "hard.5.7": "hit", "hard.8.5": "hit", "soft.19.6": "double", "hard.7.4": "hit", "soft.13.2": "hit", "hard.13.5": "stick", "pair.9.2": "stick", "pair.9.9": "stick", "soft.20.2": "stick", "pair.8.2": "split", "hard.6.2": "hit", "hard.10.6": "double", "hard.4.9": "hit", "pair.2.9": "hit", "soft.19.3": "stick", "pair.3.9": "hit", "pair.10.10": "stick", "hard.5.6": "hit", "hard.19.6": "stick", "soft.14.10": "hit", "soft.16.1": "hit", "hard.12.8": "hit", "hard.12.9": "hit", "soft.16.5": "double", "hard.21.6": "stick", "soft.20.1": "stick", "hard.19.7": "stick", "hard.9.9": "hit", "hard.17.10": "stick", "soft.13.8": "hit", "hard.10.8": "double", "hard.15.9": "hit", "soft.22.3": "stick", "soft.19.4": "stick", "pair.9.1": "stick", "pair.3.3": "hit", "pair.8.3": "split", "hard.17.9": "stick", "pair.5.9": "double", "hard.8.9": "hit", "soft.22.10": "stick", "soft.21.10": "stick", "hard.20.9": "stick", "pair.7.8": "hit", "pair.10.2": "stick", "pair.5.3": "double", "hard.19.9": "stick", "soft.18.6": "double", "soft.15.4": "double", "pair.10.8": "stick", "pair.6.3": "split", "hard.6.8": "hit", "pair.6.2": "split", "hard.11.9": "double", "soft.17.6": "double", "soft.14.5": "double", "pair.1.2": "split", "hard.14.2": "stick", "soft.18.4": "double", "soft.18.7": "stick", "pair.5.6": "double", "soft.22.5": "stick", "hard.19.5": "stick", "hard.10.3": "double", "hard.10.4": "double", "soft.22.1": "stick", "pair.8.1": "hit", "hard.17.5": "stick", "hard.5.5": "hit", "hard.13.2": "stick", "soft.14.9": "hit", "hard.7.9": "hit", "hard.8.6": "hit", "soft.21.5": "stick", "hard.12.6": "stick", "soft.19.2": "stick", "hard.20.8": "stick", "hard.9.8": "hit", "hard.5.8": "hit", "pair.7.9": "hit", "pair.5.8": "double", "hard.8.2": "hit", "hard.14.10": "hit", "hard.21.2": "stick", "pair.3.10": "hit", "pair.5.10": "hit", "hard.11.7": "double", "hard.4.1": "hit", "hard.16.5": "stick", "soft.21.3": "stick", "soft.17.8": "hit", "pair.7.5": "split", "hard.10.10": "hit", "soft.15.6": "double", "soft.19.7": "stick", "pair.9.10": "stick", "hard.21.3": "stick", "hard.16.1": "hit", "hard.6.4": "hit", "hard.4.8": "hit", "hard.12.2": "stick", "soft.13.1": "hit", "pair.3.2": "split", "hard.10.1": "hit", "hard.4.7": "hit", "soft.16.6": "double", "hard.20.4": "stick", "pair.9.4": "split", "soft.16.9": "hit", "soft.21.6": "stick", "pair.1.10": "split", "soft.14.6": "double", "hard.16.3": "stick", "soft.19.1": "stick", "soft.22.9": "stick", "soft.13.5": "hit", "hard.20.10": "stick", "hard.6.6": "hit", "hard.11.3": "double", "hard.12.7": "hit", "hard.7.3": "hit", "hard.21.4": "stick", "pair.5.2": "double", "hard.9.2": "double", "hard.7.8": "hit", "soft.21.7": "stick", "pair.4.8": "hit", "pair.2.7": "hit", "pair.10.9": "stick", "pair.2.6": "split", "hard.7.6": "hit", "soft.18.3": "double", "hard.9.4": "double", "hard.21.7": "stick", "pair.10.4": "stick", "hard.10.9": "double", "pair.1.5": "split", "soft.15.1": "hit", "hard.9.3": "double", "hard.8.10": "hit", "pair.3.6": "split", "soft.16.3": "double", "pair.8.6": "split", "hard.20.5": "stick", "soft.15.9": "hit", "hard.17.8": "stick", "hard.21.1": "stick", "hard.21.5": "stick", "pair.7.3": "split", "hard.12.4": "stick", "pair.1.9": "split", "epochs": 100000000, "hard.6.10": "hit", "pair.4.9": "hit", "hard.9.1": "hit", "hard.8.8": "hit", "hard.18.9": "stick", "hard.18.5": "stick", "soft.17.5": "double", "soft.17.2": "double", "pair.2.8": "hit", "pair.7.1": "hit", "hard.10.7": "double", "soft.22.8": "stick", "hard.14.8": "hit", "hard.17.4": "stick", "pair.6.6": "split", "hard.10.5": "double", "hard.18.10": "stick", "soft.20.3": "stick", "soft.18.5": "double", "hard.6.5": "hit", "pair.5.4": "double", "soft.13.6": "double", "soft.19.8": "stick", "pair.6.1": "hit", "hard.20.6": "stick", "pair.9.6": "split", "soft.13.9": "hit", "hard.7.2": "hit", "soft.14.8": "hit", "pair.8.7": "split", "hard.17.1": "stick", "pair.3.5": "split", "soft.21.4": "stick", "pair.10.1": "stick", "hard.11.10": "double", "pair.8.9": "split", "hard.14.9": "hit", "hard.6.3": "hit", "hard.4.10": "hit", "hard.19.2": "stick", "pair.8.4": "split", "hard.10.2": "double", "hard.18.6": "stick", "pair.7.7": "split", "hard.12.10": "hit", "pair.8.10": "stick", "hard.19.1": "stick", "hard.12.3": "stick", "hard.16.8": "hit", "pair.2.4": "split", "pair.6.8": "hit", "pair.10.3": "stick", "pair.4.7": "hit", "pair.3.4": "split", "hard.16.10": "stick", "pair.4.10": "hit", "hard.7.1": "hit", "pair.10.7": "stick", "soft.15.5": "double", "soft.18.1": "hit", "hard.8.3": "hit", "hard.19.4": "stick", "hard.21.8": "stick", "hard.14.4": "stick", "soft.20.5": "stick", "hard.11.6": "double", "hard.9.6": "double", "pair.3.1": "hit", "hard.16.7": "hit", "hard.14.5": "stick", "hard.4.6": "stick", "soft.21.8": "stick", "soft.16.7": "hit", "soft.22.4": "stick", "hard.16.6": "stick", "hard.13.4": "stick", "hard.5.1": "hit", "pair.4.6": "split", "pair.10.5": "stick", "hard.13.10": "hit", "pair.3.8": "hit", "soft.17.3": "double", "hard.9.7": "double", "hard.12.5": "stick", "pair.4.1": "hit", "pair.9.7": "stick", "hard.20.7": "stick", "pair.1.4": "split", "pair.6.4": "split", "hard.13.8": "hit", "soft.21.9": "stick", "pair.4.2": "hit", "hard.15.8": "hit", "soft.15.3": "hit", "soft.16.8": "hit", "pair.5.7": "double", "soft.19.9": "stick", "pair.1.6": "split", "hard.15.6": "stick", "pair.8.5": "split", "pair.9.3": "split", "hard.5.2": "hit", "hard.18.3": "stick", "hard.8.1": "hit", "hard.18.1": "stick", "hard.14.7": "hit", "soft.21.2": "stick", "hard.7.5": "hit", "soft.17.1": "hit", "pair.4.4": "hit", "hard.14.6": "stick", "hard.5.3": "hit", "soft.17.9": "hit", "pair.9.5": "split", "hard.15.5": "stick", "hard.15.3": "stick", "hard.5.9": "hit", "hard.9.10": "hit", "name": "my_basic", "soft.15.10": "hit", "hard.17.3": "stick", "pair.10.6": "stick", "hard.12.1": "hit", "soft.20.10": "stick", "hard.11.2": "double", "soft.18.10": "hit", "soft.18.8": "stick", "hard.15.4": "stick", "pair.3.7": "hit", "soft.20.7": "stick", "soft.16.2": "hit", "hard.13.9": "hit", "hard.11.4": "double", "soft.18.9": "hit", "hard.19.3": "stick", "soft.14.2": "hit", "soft.15.7": "hit", "hard.18.8": "stick", "hard.20.1": "stick", "pair.2.2": "hit", "soft.20.6": "stick", "soft.22.2": "stick", "pair.7.6": "split", "pair.5.1": "hit", "hard.14.1": "hit", "pair.1.7": "split", "hard.7.7": "hit", "soft.20.9": "stick", "hard.9.5": "double", "pair.2.1": "hit", "hard.16.4": "stick", "pair.1.3": "split", "hard.20.3": "stick", "hard.19.8": "stick", "pair.6.10": "hit", "soft.19.10": "stick", "hard.6.1": "hit", "hard.15.1": "hit", "hard.4.2": "stick", "pair.2.5": "split", "hard.17.7": "stick", "soft.18.2": "double", "soft.17.10": "hit", "hard.7.10": "hit", "soft.20.8": "stick", "hard.16.9": "stick", "soft.22.7": "stick", "soft.14.7": "hit", "hard.13.3": "stick", "soft.20.4": "stick", "pair.8.8": "split", "hard.5.10": "hit", "soft.17.7": "hit", "hard.16.2": "stick", "hard.21.10": "stick", "soft.15.8": "hit", "pair.7.10": "hit", "hard.4.4": "hit", "pair.7.2": "split", "pair.2.10": "hit", "hard.17.6": "stick", "hard.11.5": "double", "hard.14.3": "stick", "soft.16.4": "double", "hard.21.9": "stick", "hard.8.4": "hit", "hard.8.7": "hit", "hard.4.3": "hit", "hard.5.4": "hit", "soft.19.5": "stick", "hard.4.5": "hit", "soft.17.4": "double", "hard.11.1": "hit", "soft.14.1": "hit", "soft.13.3": "hit", "pair.6.5": "split", "hard.20.2": "stick", "pair.6.9": "hit", "hard.6.7": "hit", "hard.15.10": "hit", "soft.15.2": "hit", "hard.19.10": "stick", "hard.18.7": "stick", "pair.1.1": "hit", "hard.15.7": "hit", "soft.13.7": "hit", "pair.5.5": "double", "hard.13.7": "hit", "soft.14.4": "hit", "soft.16.10": "hit", "soft.13.10": "hit", "pair.4.3": "hit", "soft.21.1": "stick", "hard.15.2": "stick", "hard.13.1": "hit", "hard.6.9": "hit"}